isdttool/__init__.py
isdttool/__main__.py
isdttool/cli_tool.py
isdttool/tests.py
isdttool/charger/__init__.py
isdttool/charger/actions.py
isdttool/charger/charger.py
isdttool/charger/representation.py
isdttool/firmware/__init__.py
isdttool-1.0.1.dist-info/LICENSE
isdttool-1.0.1.dist-info/METADATA
isdttool-1.0.1.dist-info/WHEEL
isdttool-1.0.1.dist-info/entry_points.txt
isdttool-1.0.1.dist-info/top_level.txt
isdttool-1.0.1.dist-info/RECORD
