Metadata-Version: 2.1
Name: isdttool
Version: 1.0.1
Summary: Tool to retrieve information from ISDT chargers with USB connection.
Home-page: https://github.com/maxried/isdt
Author: Max Ried
Author-email: maxried@posteo.de
License: GPLv3
Platform: UNKNOWN
Classifier: Programming Language :: Python :: 3
Classifier: Topic :: System :: Hardware :: Hardware Drivers
Classifier: License :: OSI Approved :: GNU General Public License v3 (GPLv3)
Classifier: Operating System :: MacOS :: MacOS X
Classifier: Operating System :: POSIX :: Linux
Requires-Python: >=3.6
Requires-Dist: hidapi (~=0.10.1)
